{"version":1,"resource":"file:///home/madwayl/.dotfiles/docs/hibernate-suspend.md","entries":[{"id":"9WDR.md","source":"renamed.source","sourceDescription":"~/.dotfiles/docs/hibernate-suspend","timestamp":1748249495785},{"id":"lGjI.md","timestamp":1748249506750},{"id":"lOUV.md","timestamp":1748249538392},{"id":"sB4W.md","timestamp":1748249565032},{"id":"3VsP.md","timestamp":1748249582730},{"id":"gCyN.md","timestamp":1748249848864},{"id":"IDP0.md","timestamp":1748249871035},{"id":"5Z8x.md","timestamp":1748249898470},{"id":"1a92.md","timestamp":1748249991789},{"id":"1r7w.md","timestamp":1748250086217},{"id":"v40h.md","timestamp":1748250114959},{"id":"Nu7w.md","timestamp":1748250152851},{"id":"pgEY.md","timestamp":1748250170692},{"id":"cqJE.md","timestamp":1748250238893},{"id":"wzdU.md","timestamp":1748250273386},{"id":"gTTS.md","timestamp":1748250465328},{"id":"0OrY.md","timestamp":1748250490860},{"id":"ZvJM.md","timestamp":1748250597303},{"id":"pkfj.md","timestamp":1748250779007},{"id":"vPhb.md","timestamp":1748250964361},{"id":"wanV.md","timestamp":1748251051706},{"id":"eEH2.md","timestamp":1748254210153},{"id":"NBIG.md","timestamp":1748254230642},{"id":"JV9r.md","timestamp":1748254295122}]}