{"version":1,"resource":"file:///home/madwayl/.config/hypr/keybindings.conf","entries":[{"id":"fK6R.conf","source":"undoRedo.source","timestamp":1748029336228},{"id":"Ezjp.conf","timestamp":1748029340669},{"id":"aUID.conf","timestamp":1748029517811},{"id":"1IjU.conf","source":"undoRedo.source","timestamp":1748029526418},{"id":"S0Dz.conf","timestamp":1748029679255},{"id":"WShW.conf","timestamp":1748029832110},{"id":"McGK.conf","timestamp":1748029926493},{"id":"AypA.conf","timestamp":1748030944185},{"id":"95Hr.conf","timestamp":1748060741364},{"id":"njYQ.conf","timestamp":1748073832329},{"id":"lGQ3.conf","timestamp":1748119402863},{"id":"BFap.conf","timestamp":1748119429085},{"id":"p8XL.conf","timestamp":1748119705726},{"id":"WEvi.conf","timestamp":1748163694658},{"id":"VBYU.conf","timestamp":1748163739497},{"id":"Llds.conf","timestamp":1748166235511},{"id":"rTIB.conf","timestamp":1748166273275},{"id":"8Ks8.conf","timestamp":1748194720977},{"id":"U2Ll.conf","timestamp":1748194910585},{"id":"7Fp1.conf","source":"undoRedo.source","timestamp":1748195207419},{"id":"jSLe.conf","timestamp":1748195462689},{"id":"MvHj.conf","timestamp":1748195644630},{"id":"JOGN.conf","source":"undoRedo.source","timestamp":1748195663084},{"id":"XTAl.conf","timestamp":1748198014368},{"id":"fAQ3.conf","timestamp":1748198034146},{"id":"sHt2.conf","timestamp":1748198097734},{"id":"0zj8.conf","timestamp":1748272141686},{"id":"hlas.conf","timestamp":1748272543720},{"id":"cqRy.conf","timestamp":1748272690360},{"id":"m9hc.conf","timestamp":1748272721645},{"id":"uTk4.conf","timestamp":1748272814722},{"id":"mGWs.conf","timestamp":1748272963222},{"id":"F1no.conf","timestamp":1748273030615},{"id":"Mizf.conf","timestamp":1748273069816},{"id":"0V6t.conf","source":"undoRedo.source","timestamp":1748273074960},{"id":"HAcz.conf","timestamp":1748273086367},{"id":"gbSd.conf","source":"undoRedo.source","timestamp":1748273121470},{"id":"5G43.conf","timestamp":1748273138256},{"id":"trXR.conf","timestamp":1748273203286},{"id":"NVK8.conf","timestamp":1748273232156},{"id":"BbKM.conf","timestamp":1748278790872},{"id":"ZMLh.conf","timestamp":1748287103776},{"id":"GOw1.conf","timestamp":1748287200683},{"id":"zgIN.conf","timestamp":1748287998965},{"id":"KSZM.conf","timestamp":1748288299722},{"id":"E2vk.conf","timestamp":1748288320777},{"id":"4iqP.conf","timestamp":1748288381874},{"id":"ZLOM.conf","timestamp":1748341937353},{"id":"npZh.conf","timestamp":1748342919900},{"id":"dq8A.conf","timestamp":1748355930923}]}